{
  "framework": "react",
  "utils": {
    "cn": {
      "file": "lib/utils.ts",
      "dependencies": ["clsx", "tailwind-merge"]
    }
  },
  "provider": {
    "file": "softuq-provider.tsx",
    "dependencies": []
  },
  "components": {
    "accordion": {
      "files": ["components/ui/accordion.tsx"],
      "dependencies": ["class-variance-authority", "lucide-react"],
      "registryDeps": []
    },
    "alert": {
      "files": ["components/ui/alert.tsx"],
      "dependencies": ["class-variance-authority", "lucide-react"],
      "registryDeps": []
    },
    "avatar": {
      "files": ["components/ui/avatar.tsx"],
      "dependencies": ["class-variance-authority"],
      "registryDeps": []
    },
    "badge": {
      "files": ["components/ui/badge.tsx"],
      "dependencies": ["class-variance-authority"],
      "registryDeps": []
    },
    "breadcrumb": {
      "files": ["components/ui/breadcrumb.tsx"],
      "dependencies": ["lucide-react"],
      "registryDeps": ["dropdown-menu"]
    },
    "button": {
      "files": ["components/ui/button.tsx"],
      "dependencies": ["class-variance-authority"],
      "registryDeps": []
    },
    "card": {
      "files": ["components/ui/card.tsx"],
      "dependencies": ["class-variance-authority"],
      "registryDeps": []
    },
    "checkbox": {
      "files": ["components/ui/checkbox.tsx"],
      "dependencies": ["class-variance-authority", "lucide-react"],
      "registryDeps": []
    },
    "code": {
      "files": ["components/ui/code.tsx"],
      "dependencies": ["lucide-react"],
      "registryDeps": []
    },
    "dialog": {
      "files": ["components/ui/dialog.tsx"],
      "dependencies": ["class-variance-authority", "lucide-react"],
      "registryDeps": []
    },
    "dropdown-menu": {
      "files": ["components/ui/dropdown-menu.tsx"],
      "dependencies": ["lucide-react"],
      "registryDeps": []
    },
    "empty": {
      "files": ["components/ui/empty.tsx"],
      "dependencies": [],
      "registryDeps": []
    },
    "form-text": {
      "files": ["components/ui/form-text.tsx"],
      "dependencies": ["class-variance-authority"],
      "registryDeps": []
    },
    "input": {
      "files": ["components/ui/input.tsx"],
      "dependencies": ["class-variance-authority"],
      "registryDeps": []
    },
    "kbd": {
      "files": ["components/ui/kbd.tsx"],
      "dependencies": ["class-variance-authority"],
      "registryDeps": []
    },
    "label": {
      "files": ["components/ui/label.tsx"],
      "dependencies": ["class-variance-authority"],
      "registryDeps": []
    },
    "pagination": {
      "files": ["components/ui/pagination.tsx"],
      "dependencies": ["class-variance-authority", "lucide-react"],
      "registryDeps": []
    },
    "placeholder": {
      "files": ["components/ui/placeholder.tsx"],
      "dependencies": ["class-variance-authority", "lucide-react"],
      "registryDeps": []
    },
    "popover": {
      "files": ["components/ui/popover.tsx"],
      "dependencies": [],
      "registryDeps": []
    },
    "progress": {
      "files": ["components/ui/progress.tsx"],
      "dependencies": ["class-variance-authority"],
      "registryDeps": []
    },
    "radio": {
      "files": ["components/ui/radio.tsx"],
      "dependencies": ["class-variance-authority"],
      "registryDeps": []
    },
    "select": {
      "files": ["components/ui/select.tsx"],
      "dependencies": ["class-variance-authority", "lucide-react"],
      "registryDeps": ["tag"]
    },
    "search": {
      "files": ["components/ui/search.tsx"],
      "dependencies": ["class-variance-authority", "lucide-react"],
      "registryDeps": ["kbd", "tag"]
    },
    "separator": {
      "files": ["components/ui/separator.tsx"],
      "dependencies": [],
      "registryDeps": []
    },
    "sheet": {
      "files": ["components/ui/sheet.tsx"],
      "dependencies": ["class-variance-authority", "lucide-react"],
      "registryDeps": []
    },
    "skeleton": {
      "files": ["components/ui/skeleton.tsx"],
      "dependencies": ["class-variance-authority"],
      "registryDeps": []
    },
    "slider": {
      "files": ["components/ui/slider.tsx"],
      "dependencies": ["class-variance-authority"],
      "registryDeps": []
    },
    "spinner": {
      "files": ["components/ui/spinner.tsx"],
      "dependencies": ["class-variance-authority", "lucide-react"],
      "registryDeps": []
    },
    "squircle": {
      "files": ["components/ui/squircle.tsx", "lib/squircle.ts"],
      "dependencies": [],
      "registryDeps": []
    },
    "table": {
      "files": ["components/ui/table.tsx"],
      "dependencies": [],
      "registryDeps": []
    },
    "tabs": {
      "files": ["components/ui/tabs.tsx"],
      "dependencies": [],
      "registryDeps": []
    },
    "tag": {
      "files": ["components/ui/tag.tsx"],
      "dependencies": ["class-variance-authority", "lucide-react"],
      "registryDeps": []
    },
    "textarea": {
      "files": ["components/ui/textarea.tsx"],
      "dependencies": ["class-variance-authority"],
      "registryDeps": []
    },
    "toast": {
      "files": ["components/ui/toast.tsx"],
      "dependencies": ["lucide-react"],
      "registryDeps": []
    },
    "toggle": {
      "files": ["components/ui/toggle.tsx"],
      "dependencies": ["class-variance-authority"],
      "registryDeps": []
    },
    "toggle-group": {
      "files": ["components/ui/toggle-group.tsx"],
      "dependencies": ["class-variance-authority"],
      "registryDeps": []
    },
    "tooltip": {
      "files": ["components/ui/tooltip.tsx"],
      "dependencies": [],
      "registryDeps": []
    }
  }
}
